{
    "namespace": "PeerReview",
    "resourceId": "PeerReview",
    "entityTypeNames": {
        "user": "User",
        "group": "UserGroup",
        "application": "Application",
        "action": "Action"
    },
    "policies": [
        {
            "id": "AdminStatusAccess",
            "groupName": "Admin",
            "actionId": "get /api/submission/status",
            "description": "Allow Admin to access submission status"
        },
        {
            "id": "GuestTimeAccess",
            "groupName": "Guest",
            "actionId": "get /api/submission/time",
            "description": "Allow Guest to access submission time"
        }
    ]
}